sqlalchemy_postgres_point/__init__.py
sqlalchemy_postgres_point/point.py
sqlalchemy_postgres_point/utils.py
sqlalchemy_postgres_point-0.1.0.dist-info/WHEEL
sqlalchemy_postgres_point-0.1.0.dist-info/METADATA
sqlalchemy_postgres_point-0.1.0.dist-info/RECORD
