Metadata-Version: 2.3
Name: sqlalchemy-postgres-point
Version: 0.1.0
Summary: Lightweight SQLAlchemy custom type for PostgreSQL POINT columns with tuple binding and an earth-distance comparator.
Keywords: sqlalchemy,postgresql,point,geometry,geospatial,gis,database,types,earthdistance
Author: Michael Bianco
Author-email: Michael Bianco <mike@mikebian.co>
Requires-Dist: sqlalchemy>=2.0
Requires-Python: >=3.10
Project-URL: Repository, https://github.com/iloveitaly/sqlalchemy-postgres-point
